impact_index-0.27.4.dist-info/METADATA
impact_index-0.27.4.dist-info/WHEEL
impact_index-0.27.4.dist-info/licenses/LICENSE.txt
impact_index/__init__.py
impact_index/impact_index.pyd
impact_index-0.27.4.dist-info/RECORD
