Metadata-Version: 2.4
Name: impact-index
Version: 0.27.4
Classifier: Programming Language :: Rust
Classifier: Programming Language :: Python :: Implementation :: CPython
Classifier: Programming Language :: Python :: Implementation :: PyPy
License-File: LICENSE.txt
Author-email: Benjamin Piwowarski <benjamin@piwowarski.fr>
Requires-Python: >=3.8
